rookie_stock_crawler/__init__.py
rookie_stock_crawler/database.py
rookie_stock_crawler/extensions.py
rookie_stock_crawler/process.py
rookie_stock_crawler/stock.py
rookie_stock_crawler/utils.py
rookie_stock_crawler-0.1.0.dist-info/LICENSE
rookie_stock_crawler-0.1.0.dist-info/METADATA
rookie_stock_crawler-0.1.0.dist-info/WHEEL
rookie_stock_crawler-0.1.0.dist-info/top_level.txt
rookie_stock_crawler-0.1.0.dist-info/RECORD
