Metadata-Version: 2.1
Name: rookie-stock-crawler
Version: 0.1.0
Summary: A light weight tool to crawl stock data from yahoo finance.
Home-page: https://github.com/nichujie/py-stock-crawler
Author: Cheney Ni
Author-email: ncj19991213@126.com
License: UNKNOWN
Platform: UNKNOWN
Classifier: Programming Language :: Python :: 3
Classifier: License :: OSI Approved :: MIT License
Classifier: Operating System :: OS Independent
Requires-Dist: requests
Requires-Dist: beautifulsoup4
Requires-Dist: psycopg2
Requires-Dist: psycopg2-binary
